dapla_suv_tools/__init__.py
dapla_suv_tools/_internals/__init__.py
dapla_suv_tools/_internals/client_apis/__init__.py
dapla_suv_tools/_internals/client_apis/innkvittering_api.py
dapla_suv_tools/_internals/client_apis/instans_api.py
dapla_suv_tools/_internals/client_apis/instantiator_api.py
dapla_suv_tools/_internals/client_apis/periode_api.py
dapla_suv_tools/_internals/client_apis/prefill_api_stat_api.py
dapla_suv_tools/_internals/client_apis/prefill_meta_api.py
dapla_suv_tools/_internals/client_apis/pulje_api.py
dapla_suv_tools/_internals/client_apis/sfu_api.py
dapla_suv_tools/_internals/client_apis/skjema_api.py
dapla_suv_tools/_internals/client_apis/utsending_api.py
dapla_suv_tools/_internals/integration/__init__.py
dapla_suv_tools/_internals/integration/api_client.py
dapla_suv_tools/_internals/integration/lab_id_client.py
dapla_suv_tools/_internals/integration/user_tools.py
dapla_suv_tools/_internals/util/__init__.py
dapla_suv_tools/_internals/util/constants.py
dapla_suv_tools/_internals/util/dateUtils.py
dapla_suv_tools/_internals/util/decorators.py
dapla_suv_tools/_internals/util/help_helper.py
dapla_suv_tools/_internals/util/helpers.py
dapla_suv_tools/_internals/util/operation_result.py
dapla_suv_tools/_internals/util/suv_operation_context.py
dapla_suv_tools/_internals/util/validators.py
dapla_suv_tools/pagination.py
dapla_suv_tools/suv_client.py
dapla_suv_tools-0.1.85.dist-info/METADATA
dapla_suv_tools-0.1.85.dist-info/WHEEL
dapla_suv_tools-0.1.85.dist-info/licenses/LICENSE
dapla_suv_tools-0.1.85.dist-info/RECORD
