Metadata-Version: 2.4
Name: dapla-suv-tools
Version: 0.1.85
Summary: 
License-File: LICENSE
Author: Anders Hagen
Author-email: nhk@ssb.no
Requires-Python: >=3.10,<4.0
Classifier: Programming Language :: Python :: 3
Classifier: Programming Language :: Python :: 3.10
Classifier: Programming Language :: Python :: 3.11
Classifier: Programming Language :: Python :: 3.12
Classifier: Programming Language :: Python :: 3.13
Classifier: Programming Language :: Python :: 3.14
Requires-Dist: dapla-auth-client (>=1.0.1,<2.0.0)
Requires-Dist: python-dateutil (>=2.9.0.post0,<3.0.0)
Requires-Dist: pytz (>=2025.2,<2026.0)
Requires-Dist: requests (>=2.31.0,<3.0.0)
Requires-Dist: ssb-altinn3-util (>=0.0.82,<0.0.83)
Requires-Dist: starlette (>=0.49.1,<0.50.0)
